motus/__init__.py
motus/atomic_io.py
motus/checkpoint.py
motus/checkpoint_models.py
motus/checkpoint_storage.py
motus/claims.py
motus/config.py
motus/config_loader.py
motus/config_schema.py
motus/decisions.py
motus/decisions_core.py
motus/decisions_storage.py
motus/defaults.yaml
motus/drift_detector_core.py
motus/drift_detector_patterns.py
motus/ethos.py
motus/events.py
motus/exceptions.py
motus/file_lock.py
motus/gemini_hooks.py
motus/harness.py
motus/harness_core.py
motus/harness_runners.py
motus/hooks.py
motus/hooks_context.py
motus/intent.py
motus/intent_models.py
motus/intent_parser_core.py
motus/intent_parser_yaml.py
motus/logging.py
motus/messages.py
motus/motus_fs.py
motus/process_detector.py
motus/protocols.py
motus/protocols_builder.py
motus/protocols_enums.py
motus/protocols_models.py
motus/protocols_models_core.py
motus/protocols_models_types.py
motus/protocols_utils.py
motus/py.typed
motus/scope.py
motus/session_cache.py
motus/session_identity.py
motus/session_ingestion.py
motus/session_query.py
motus/session_store.py
motus/session_store_core.py
motus/session_store_queries.py
motus/subprocess_utils.py
motus/tail_reader.py
motus/tracer.py
motus/api/__init__.py
motus/api/facade.py
motus/api/resilience.py
motus/bench/__init__.py
motus/bench/__main__.py
motus/bench/_adversarial_builders.py
motus/bench/_adversarial_fixture.py
motus/bench/_adversarial_helpers.py
motus/bench/_git_utils.py
motus/bench/adversarial_suite_v0_1.py
motus/bench/eval_artifacts.py
motus/bench/harness.py
motus/bench/harness_runner.py
motus/bench/harness_types.py
motus/bench/kernel_suite_v0_1.py
motus/capabilities/__init__.py
motus/capabilities/loader.py
motus/capabilities/loader_cache.py
motus/cli/__init__.py
motus/cli/__main__.py
motus/cli/_traces.py
motus/cli/core.py
motus/cli/exit_codes.py
motus/cli/formatters.py
motus/cli/help.py
motus/cli/output.py
motus/cli/output_converters.py
motus/cli/output_types.py
motus/cli/session_utils.py
motus/cli/validators.py
motus/cli/watch_cmd.py
motusos-0.1.1.dist-info/METADATA
motusos-0.1.1.dist-info/WHEEL
motusos-0.1.1.dist-info/entry_points.txt
motusos-0.1.1.dist-info/licenses/LICENSE
motusos-0.1.1.dist-info/licenses/NOTICE
motusos-0.1.1.dist-info/RECORD
