Metadata-Version: 2.4
Name: motusos
Version: 0.1.1
Summary: Command Center for AI Agents - Real-time observability for Claude Code, Codex CLI, and AI coding assistants
Project-URL: Homepage, https://github.com/motus-os/motus
Project-URL: Documentation, https://github.com/motus-os/motus#readme
Project-URL: Repository, https://github.com/motus-os/motus
Project-URL: Issues, https://github.com/motus-os/motus/issues
Author: Veritas Collaborative, LLC
License: Motus Community Source License (MCSL) v0.1
License-File: LICENSE
License-File: NOTICE
Keywords: agents,ai,claude,cli,codex,dashboard,developer-tools,gemini,llm,monitoring,observability,tracing,tui
Classifier: Development Status :: 4 - Beta
Classifier: Environment :: Console
Classifier: Intended Audience :: Developers
Classifier: License :: Other/Proprietary License
Classifier: Operating System :: OS Independent
Classifier: Programming Language :: Python :: 3
Classifier: Programming Language :: Python :: 3.10
Classifier: Programming Language :: Python :: 3.11
Classifier: Programming Language :: Python :: 3.12
Classifier: Topic :: Software Development :: Libraries :: Python Modules
Classifier: Topic :: System :: Monitoring
Requires-Python: >=3.10
Requires-Dist: httpx>=0.25.0
Requires-Dist: jsonschema>=4.0
Requires-Dist: psutil>=5.9.0
Requires-Dist: pydantic>=2.0.0
Requires-Dist: pyyaml>=6.0
Requires-Dist: rich>=13.0.0
Provides-Extra: dev
Requires-Dist: beautifulsoup4>=4.12.0; extra == 'dev'
Requires-Dist: black>=23.0.0; extra == 'dev'
Requires-Dist: build>=1.0.0; extra == 'dev'
Requires-Dist: fastapi>=0.100.0; extra == 'dev'
Requires-Dist: mypy>=1.8.0; extra == 'dev'
Requires-Dist: pip-audit>=2.7.0; extra == 'dev'
Requires-Dist: pre-commit>=3.0.0; extra == 'dev'
Requires-Dist: pytest-asyncio>=1.0.0; extra == 'dev'
Requires-Dist: pytest-cov>=4.0.0; extra == 'dev'
Requires-Dist: pytest-timeout>=2.2.0; extra == 'dev'
Requires-Dist: pytest-xdist>=3.5.0; extra == 'dev'
Requires-Dist: pytest>=7.0.0; extra == 'dev'
Requires-Dist: ruff>=0.1.0; extra == 'dev'
Requires-Dist: syrupy>=4.0.0; extra == 'dev'
Requires-Dist: types-pyyaml>=6.0.12; extra == 'dev'
Provides-Extra: gemini
Requires-Dist: google-genai>=0.3.0; extra == 'gemini'
Provides-Extra: mcp
Requires-Dist: mcp>=1.2.0; extra == 'mcp'
Provides-Extra: web
Requires-Dist: fastapi>=0.100.0; extra == 'web'
Requires-Dist: uvicorn>=0.23.0; extra == 'web'
Requires-Dist: websockets>=11.0; extra == 'web'
